simple_bank_korea/__init__.py
simple_bank_korea/kb/__init__.py
simple_bank_korea/kb/crawler.py
simple_bank_korea/kb/image_checker.py
simple_bank_korea/kb/assets/.DS_Store
simple_bank_korea/kb/assets/0.png
simple_bank_korea/kb/assets/5.png
simple_bank_korea/kb/assets/7.png
simple_bank_korea/kb/assets/8.png
simple_bank_korea/kb/assets/9.png
simple_bank_korea-0.2.8.dist-info/DESCRIPTION.rst
simple_bank_korea-0.2.8.dist-info/METADATA
simple_bank_korea-0.2.8.dist-info/RECORD
simple_bank_korea-0.2.8.dist-info/WHEEL
simple_bank_korea-0.2.8.dist-info/metadata.json
simple_bank_korea-0.2.8.dist-info/top_level.txt
