Metadata-Version: 2.0
Name: simple-bank-korea
Version: 0.2.8
Summary: Crawling Korea bank transactions
Home-page: https://github.com/beomi/simple_bank_korea
Author: Junbum Lee
Author-email: jun@beomi.net
License: MIT
Download-URL: https://github.com/beomi/simple_bank_korea/archive/0.2.8.tar.gz
Platform: UNKNOWN
Requires-Dist: python-dateutil
Requires-Dist: requests
Requires-Dist: bs4
Requires-Dist: selenium
Requires-Dist: pillow
